dinkum/__init__.py
dinkum/exceptions.py
dinkum/log.py
dinkum/observations.py
dinkum/utils.py
dinkum/vfg.py
dinkum/vfg_functions.py
dinkum/vfn.py
dinkum/display/__init__.py
dinkum/display/draw_ipycanvas.py
dinkum/display/draw_pillow.py
dinkum/display/widgets.py
dinkum_bio-0.6.1.dist-info/licenses/LICENSE
tests/test_bad_conditions.py
tests/test_custom_activation_fn.py
tests/test_misc.py
tests/test_output_btp.py
tests/test_python_api.py
tests/test_receptor.py
tests/test_simple.py
tests/test_vfg_functions.py
dinkum_bio-0.6.1.dist-info/METADATA
dinkum_bio-0.6.1.dist-info/WHEEL
dinkum_bio-0.6.1.dist-info/top_level.txt
dinkum_bio-0.6.1.dist-info/RECORD
