Metadata-Version: 2.4
Name: dinkum-bio
Version: 0.6.1
Summary: directed interaction network kit for modeling, focused on GRNs
Author: C. Titus Brown
Classifier: Programming Language :: Python :: Implementation :: CPython
Classifier: License :: OSI Approved :: GNU Affero General Public License v3 or later (AGPLv3+)
Requires-Python: >=3.11
License-File: LICENSE
Requires-Dist: ipycanvas==0.13.3
Requires-Dist: Pillow==10.2.0
Requires-Dist: pandas<3,>=2
Requires-Dist: matplotlib
Requires-Dist: lmfit
Requires-Dist: emcee
Provides-Extra: test
Requires-Dist: nbval==0.11.0; extra == "test"
Requires-Dist: pytest; extra == "test"
Dynamic: license-file
